torchqdynamics/foo.py
torchqdynamics-0.1.0.dist-info/METADATA
torchqdynamics-0.1.0.dist-info/WHEEL
torchqdynamics-0.1.0.dist-info/top_level.txt
torchqdynamics-0.1.0.dist-info/RECORD
