Metadata-Version: 2.1
Name: torchqdynamics
Version: 0.1.0
Summary: Coming soon!
Author-email: Pierre Guilmin <pierreguilmin@gmail.com>
